topapprox/__init__.py
topapprox/filter_graph.py
topapprox/filter_image.py
topapprox/link_reduce.py
topapprox-0.0.2.dist-info/METADATA
topapprox-0.0.2.dist-info/WHEEL
topapprox-0.0.2.dist-info/licenses/LICENSE
topapprox-0.0.2.dist-info/RECORD
