Metadata-Version: 2.3
Name: topapprox
Version: 0.0.2
Summary: Package for computing topological filtering of singals over networks using Persistent Homology.
Project-URL: Homepage, https://github.com/mvlier/topapprox
Project-URL: Issues, https://github.com/mvlier/topapprox/issues
Author: Junyan Chu, Sebastían Elías Graiff Zurita
Author-email: Matias de Jong van Lier <matias.vanlier@gmail.com>, Shizuo Kaji <shizuo.kaji@gmail.com>
License-File: LICENSE
Classifier: License :: OSI Approved :: MIT License
Classifier: Operating System :: OS Independent
Classifier: Programming Language :: Python :: 3
Requires-Python: >=3.8
